malhpy.py
malhpy-0.0.3.dist-info/METADATA
malhpy-0.0.3.dist-info/WHEEL
malhpy-0.0.3.dist-info/top_level.txt
malhpy-0.0.3.dist-info/RECORD
