Metadata-Version: 2.1
Name: malhpy
Version: 0.0.3
Summary: Краткое описание вашего пакета
Home-page: https://github.com/ваш_пользователь_на_github/my_package
Author: Ваше Имя
Author-email: ваш_email@example.com
Classifier: Programming Language :: Python :: 3
Classifier: License :: OSI Approved :: MIT License
Classifier: Operating System :: OS Independent
Requires-Python: >=3.6
